setup.py
ct_rest/__init__.py
ct_rest/utils.py
ct_rest/wrapper.py
ct_rest.egg-info/PKG-INFO
ct_rest.egg-info/SOURCES.txt
ct_rest.egg-info/dependency_links.txt
ct_rest.egg-info/requires.txt
ct_rest.egg-info/top_level.txt