Metadata-Version: 1.0
Name: ct-rest
Version: 0.1.6
Summary: a rest utils for ctcloud using Django
Home-page: https://github.com/astwyg/ct-rest
Author: astwyg
Author-email: i@ysgh.net
License: MIT License
Keywords: django,ctcloud,rest,ct_rest,chinatelecom
Platform: any
